impuestito/__init__.py
impuestito/main.py
impuestito-0.4b0.dist-info/METADATA
impuestito-0.4b0.dist-info/WHEEL
impuestito-0.4b0.dist-info/top_level.txt
impuestito-0.4b0.dist-info/RECORD
