Metadata-Version: 2.1
Name: impuestito
Version: 0.4b0
Summary: Impuestito es una API local para calcular impuestos al hacer compras al exterior,
Home-page: https://github.com/PinaYTTT/impuestito
Author: PinaYT
Author-email: contacto.pinayt@gmail.com
License: MIT
Download-URL: https://github.com/PinaYTTT/impuestito
Keywords: impuestos,argentina,dolar
Platform: UNKNOWN
Requires-Dist: requests
